rescomp/DrivenResComp.py
rescomp/ResComp.py
rescomp/__init__.py
rescomp/chaosode.py
rescomp/complex_networks.py
rescomp/utils.py
rescomp/opt_then_test/__init__.py
rescomp/opt_then_test/__main__.py
rescomp/opt_then_test/script_args.py
rescomp/optimizer/__init__.py
rescomp/optimizer/optimizer_controller.py
rescomp/optimizer/optimizer_functions.py
rescomp/optimizer/optimizer_systems.py
rescomp/optimizer/templates.py
rescomp/optimizer/data/__init__.py
rescomp/optimizer/data/bellows_arm1_whitened.mat
rescomp/optimizer/data/bellows_arm_whitened.mat
rescomp/optimizer/data/lorenz_prior.pkl
rescomp/optimizer/data/rossler_prior.pkl
rescomp/optimizer/data/softrobot_prior.pkl
rescomp/optimizer/data/thomas_prior.pkl
tests/__init__.py
tests/test_DrivenResComp.py
tests/test_ResComp.py
tests/test_extras.py
rescomp-0.2.1.dist-info/LICENSE
rescomp-0.2.1.dist-info/METADATA
rescomp-0.2.1.dist-info/WHEEL
rescomp-0.2.1.dist-info/top_level.txt
rescomp-0.2.1.dist-info/RECORD
