Metadata-Version: 2.1
Name: rescomp
Version: 0.2.1
Summary: A reservoir computer and chaotic systems package
Home-page: https://github.com/djpasseyjr/rescomp
Author: DJ Passey
Author-email: djpasseyjr@unc.edu
License: UNKNOWN
Platform: UNKNOWN
Classifier: Programming Language :: Python :: 3
Classifier: Operating System :: OS Independent
Requires-Python: >=3.6
Requires-Dist: numpy
Requires-Dist: networkx
Requires-Dist: scipy
Requires-Dist: numdifftools
Requires-Dist: matplotlib
Requires-Dist: findiff
Requires-Dist: dill
Requires-Dist: parameter-sherpa
Requires-Dist: ipyparallel
